README.rst
setup.cfg
setup.py
mdx_smartypants/__init__.py
mdx_smartypants/core.py
mdx_smartypants/guesslang.py
mdx_smartypants/spants.py
mdx_smartypants.egg-info/PKG-INFO
mdx_smartypants.egg-info/SOURCES.txt
mdx_smartypants.egg-info/dependency_links.txt
mdx_smartypants.egg-info/not-zip-safe
mdx_smartypants.egg-info/requires.txt
mdx_smartypants.egg-info/top_level.txt
test/test.py
test/test_spants.py