Metadata-Version: 1.0
Name: mdx-smartypants
Version: 1.5.1
Summary: Python-Markdown extension using smartypants to emit typographically nicer ("curly") quotes, proper ("em" and "en") dashes, etc.
Home-page: http://bitbucket.org/jeunice/mdx_smartypants
Author: Jonathan Eunice
Author-email: jonathan.eunice@gmail.com
License: UNKNOWN
Keywords: markdown smartypants extension curly quotes typographic
Platform: UNKNOWN
Classifier: Development Status :: 5 - Production/Stable
Classifier: Operating System :: OS Independent
Classifier: License :: OSI Approved :: BSD License
Classifier: Intended Audience :: Developers
Classifier: Environment :: Web Environment
Classifier: Programming Language :: Python
Classifier: Programming Language :: Python :: 2.6
Classifier: Programming Language :: Python :: 2.7
Classifier: Programming Language :: Python :: 3
Classifier: Programming Language :: Python :: 3.3
Classifier: Programming Language :: Python :: Implementation :: CPython
Classifier: Programming Language :: Python :: Implementation :: PyPy
Classifier: Topic :: Text Processing :: Filters
Classifier: Topic :: Text Processing :: Markup
Classifier: Topic :: Text Processing :: Markup :: HTML
